aiorabbit/__init__.py
aiorabbit/__version__.py
aiorabbit/channel0.py
aiorabbit/client.py
aiorabbit/exceptions.py
aiorabbit/message.py
aiorabbit/protocol.py
aiorabbit/state.py
aiorabbit/types.py
aiorabbit-1.0.0.dist-info/LICENSE
aiorabbit-1.0.0.dist-info/METADATA
aiorabbit-1.0.0.dist-info/WHEEL
aiorabbit-1.0.0.dist-info/top_level.txt
aiorabbit-1.0.0.dist-info/zip-safe
aiorabbit-1.0.0.dist-info/RECORD
