Metadata-Version: 2.1
Name: aiorabbit
Version: 1.0.0
Summary: An AsyncIO RabbitMQ Client Library
Home-page: https://github.com/gmr/aiorabbit
Author: Gavin M. Roy
Author-email: gavinmroy@gmail.com
License: BSD 3-Clause License
Project-URL: Bug Tracker, https://github.com/gmr/aiorabbit/issues
Project-URL: Documentation, https://aiorabbit.readthedocs.io
Project-URL: Source Code, https://github.com/gmr/aiorabbit/
Keywords: amqp,rabbitmq
Classifier: Development Status :: 3 - Alpha
Classifier: Intended Audience :: Developers
Classifier: License :: OSI Approved :: BSD License
Classifier: Natural Language :: English
Classifier: Operating System :: OS Independent
Classifier: Programming Language :: Python :: 3
Classifier: Programming Language :: Python :: 3.7
Classifier: Programming Language :: Python :: 3.8
Classifier: Programming Language :: Python :: 3.9
Classifier: Topic :: Communications
Classifier: Topic :: Internet
Classifier: Topic :: Software Development
Classifier: Typing :: Typed
License-File: LICENSE
Requires-Dist: pamqp (<4,>=3.0.0a6)
Requires-Dist: yarl (<2,>=1.4.2)
Provides-Extra: test
Requires-Dist: coverage ; extra == 'test'
Requires-Dist: flake8 ; extra == 'test'
Requires-Dist: flake8-comprehensions ; extra == 'test'
Requires-Dist: flake8-deprecated ; extra == 'test'
Requires-Dist: flake8-import-order ; extra == 'test'
Requires-Dist: flake8-print ; extra == 'test'
Requires-Dist: flake8-quotes ; extra == 'test'
Requires-Dist: flake8-rst-docstrings ; extra == 'test'
Requires-Dist: flake8-tuple ; extra == 'test'
Requires-Dist: mypy ; extra == 'test'
Requires-Dist: pygments ; extra == 'test'
Requires-Dist: pytest ; extra == 'test'
